phonevalidator/__init__.py
phonevalidator/phonevalidator.py
phonevalidator/test/__init__.py
phonevalidator/test/test_phonevalidator.py
phonevalidator-1.1.2.dist-info/DESCRIPTION.rst
phonevalidator-1.1.2.dist-info/METADATA
phonevalidator-1.1.2.dist-info/RECORD
phonevalidator-1.1.2.dist-info/WHEEL
phonevalidator-1.1.2.dist-info/metadata.json
phonevalidator-1.1.2.dist-info/top_level.txt
