Metadata-Version: 1.1
Name: phonevalidator
Version: 1.1.2
Summary: Custom cerberus.Validator for phone numbers
Home-page: https://phonevalidator.readthedocs.io/en/latest/
Author: Michael Housh
Author-email: mhoush@houshhomeenergy.com
License: MIT license
Keywords: phonevalidator
Platform: UNKNOWN
Classifier: Development Status :: 2 - Pre-Alpha
Classifier: Intended Audience :: Developers
Classifier: License :: OSI Approved :: MIT License
Classifier: Natural Language :: English
Classifier: Programming Language :: Python :: 2
Classifier: Programming Language :: Python :: 2.6
Classifier: Programming Language :: Python :: 2.7
Classifier: Programming Language :: Python :: 3
Classifier: Programming Language :: Python :: 3.3
Classifier: Programming Language :: Python :: 3.4
Classifier: Programming Language :: Python :: 3.5
